RapidanAPI/__init__.py
RapidanAPI/api.py
RapidanAPI-1.1.3.dist-info/LICENSE
RapidanAPI-1.1.3.dist-info/METADATA
RapidanAPI-1.1.3.dist-info/WHEEL
RapidanAPI-1.1.3.dist-info/top_level.txt
RapidanAPI-1.1.3.dist-info/RECORD
