Metadata-Version: 2.1
Name: RapidanAPI
Version: 1.1.3
Summary: RapidanAPI allows Rapidan Energy Group's clients to conveniently pull energy data.
Home-page: https://github.com/Justin-Diamond/RapidanAPI
Author: Justin Diamond
Author-email: justin.diamond@rapidanenergy.com
Classifier: Programming Language :: Python :: 3
Classifier: License :: OSI Approved :: Apache Software License
Classifier: Operating System :: OS Independent
Requires-Python: >=3.6
License-File: LICENSE
Requires-Dist: requests
Requires-Dist: pandas
Provides-Extra: dev
Requires-Dist: flake8; extra == "dev"
Requires-Dist: twine; extra == "dev"
Requires-Dist: wheel; extra == "dev"
